viol/__init__.py
viol/core.py
viol/server.py
viol/components/__init__.py
viol/components/button.py
viol/components/navbar.py
viol/static/css/bootstrap.min.css
viol/static/js/bootstrap.min.js
viol/static/js/htmx.min.js
viol/templates/index.html
viol-0.0.1.dist-info/METADATA
viol-0.0.1.dist-info/WHEEL
viol-0.0.1.dist-info/licenses/LICENSE.txt
viol-0.0.1.dist-info/RECORD
