Metadata-Version: 2.4
Name: viol
Version: 0.0.1
Summary: An application building platform on top of Flask and HTMLX.
Project-URL: Documentation, https://github.com/ysenarath/viol#readme
Project-URL: Issues, https://github.com/ysenarath/viol/issues
Project-URL: Source, https://github.com/ysenarath/viol
Author-email: Yasas Senarath <12231659+ysenarath@users.noreply.github.com>
License-Expression: MIT
License-File: LICENSE.txt
Classifier: Development Status :: 4 - Beta
Classifier: Programming Language :: Python
Classifier: Programming Language :: Python :: 3.8
Classifier: Programming Language :: Python :: 3.9
Classifier: Programming Language :: Python :: 3.10
Classifier: Programming Language :: Python :: 3.11
Classifier: Programming Language :: Python :: 3.12
Classifier: Programming Language :: Python :: Implementation :: CPython
Classifier: Programming Language :: Python :: Implementation :: PyPy
Requires-Python: >=3.8
Requires-Dist: flask>=3.0.3
